rrgb/__init__.py
rrgb/rrgb.py
rrgb/data/rr.pkl.gz
rrgb/tests/__init__.py
rrgb/tests/baseline_test.py
greenbook_shocks-0.0.2.dist-info/METADATA
greenbook_shocks-0.0.2.dist-info/WHEEL
greenbook_shocks-0.0.2.dist-info/top_level.txt
greenbook_shocks-0.0.2.dist-info/RECORD
