Metadata-Version: 2.1
Name: greenbook-shocks
Version: 0.0.2
Summary: Estimates the Greenbook narrative shocks
Home-page: https://github.com/joe5saia/GreenbookNarrativeShocks
Author: Joe Saia
Author-email: joe5saia@gmail.com
License: UNKNOWN
Platform: UNKNOWN
Classifier: Programming Language :: Python :: 3
Classifier: License :: OSI Approved :: MIT License
Classifier: Operating System :: OS Independent
Requires-Python: >=3.9
Requires-Dist: openpyxl
Requires-Dist: sklearn
Requires-Dist: datapungi-fed
Requires-Dist: urllib3
Requires-Dist: bs4
